{
	"VALUEHISTORY": {
		"PERSONID": 7690966,
		"IPP": "10184273",
		"FULLNAME": "AHNTEST, ANGELATU",
		"BIRTHDATE": "15-12-1845",
		"AGE": "",
		"VALUELIST": [{
			"VALUE": "152",
			"DATE": "11-02-2017",
			"ENCOUNTERID" : 13433297,
			"IEP" : "201461480",
			"UF" : "",
			"ENCOUNTERDATE" : ""
		},{
			"VALUE": "152",
			"DATE": "09-02-2017",
			"ENCOUNTERID" : 13433296,
			"IEP" : "201461480",
			"UF" : "",
			"ENCOUNTERDATE" : ""
		}, {
			"VALUE": "152",
			"DATE": "09-02-2017",
			"ENCOUNTERID": 13433296,
			"IEP": "201461480",
			"UF": "",
			"ENCOUNTERDATE": ""
		}, {
			"VALUE": "150",
			"DATE": "08-02-2017",
			"ENCOUNTERID": 13433296,
			"IEP": "201461480",
			"UF": "",
			"ENCOUNTERDATE": ""
		}, {
			"VALUE": "150",
			"DATE": "08-02-2017",
			"ENCOUNTERID": 13433296,
			"IEP": "201461480",
			"UF": "",
			"ENCOUNTERDATE": ""
		}, {
			"VALUE": "150",
			"DATE": "08-02-2017",
			"ENCOUNTERID": 13433296,
			"IEP": "201461480",
			"UF": "",
			"ENCOUNTERDATE": ""
		}, {
			"VALUE": "150",
			"DATE": "08-02-2017",
			"ENCOUNTERID": 13433296,
			"IEP": "201461480",
			"UF": "",
			"ENCOUNTERDATE": ""
		}, {
			"VALUE": "150",
			"DATE": "08-02-2017",
			"ENCOUNTERID": 13433296,
			"IEP": "201461480",
			"UF": "",
			"ENCOUNTERDATE": ""
		}, {
			"VALUE": "150",
			"DATE": "07-02-2017",
			"ENCOUNTERID": 13433296,
			"IEP": "201461480",
			"UF": "",
			"ENCOUNTERDATE": ""
		}, {
			"VALUE": "150",
			"DATE": "26-01-2017",
			"ENCOUNTERID": 13433296,
			"IEP": "201461480",
			"UF": "",
			"ENCOUNTERDATE": ""
		}, {
			"VALUE": "150",
			"DATE": "26-01-2017",
			"ENCOUNTERID": 13433296,
			"IEP": "201461480",
			"UF": "",
			"ENCOUNTERDATE": ""
		}, {
			"VALUE": "150",
			"DATE": "26-01-2017",
			"ENCOUNTERID": 13433296,
			"IEP": "201461480",
			"UF": "",
			"ENCOUNTERDATE": ""
		}, {
			"VALUE": "150",
			"DATE": "26-01-2017",
			"ENCOUNTERID": 13433296,
			"IEP": "201461480",
			"UF": "",
			"ENCOUNTERDATE": ""
		}, {
			"VALUE": "150",
			"DATE": "26-01-2017",
			"ENCOUNTERID": 13433296,
			"IEP": "201461480",
			"UF": "",
			"ENCOUNTERDATE": ""
		}, {
			"VALUE": "150",
			"DATE": "26-01-2017",
			"ENCOUNTERID": 13433296,
			"IEP": "201461480",
			"UF": "",
			"ENCOUNTERDATE": ""
		}, {
			"VALUE": "150",
			"DATE": "26-01-2017",
			"ENCOUNTERID": 13433296,
			"IEP": "201461480",
			"UF": "",
			"ENCOUNTERDATE": ""
		}, {
			"VALUE": "150",
			"DATE": "26-01-2017",
			"ENCOUNTERID": 13433296,
			"IEP": "201461480",
			"UF": "",
			"ENCOUNTERDATE": ""
		}, {
			"VALUE": "150",
			"DATE": "15-09-2016",
			"ENCOUNTERID": 13433296,
			"IEP": "201461480",
			"UF": "",
			"ENCOUNTERDATE": ""
		}, {
			"VALUE": "115",
			"DATE": "14-09-2016",
			"ENCOUNTERID": 13433296,
			"IEP": "201461480",
			"UF": "",
			"ENCOUNTERDATE": ""
		}, {
			"VALUE": "152",
			"DATE": "14-09-2016",
			"ENCOUNTERID": 13433296,
			"IEP": "201461480",
			"UF": "",
			"ENCOUNTERDATE": ""
		}, {
			"VALUE": "122",
			"DATE": "14-09-2016",
			"ENCOUNTERID": 13433296,
			"IEP": "201461480",
			"UF": "",
			"ENCOUNTERDATE": ""
		}, {
			"VALUE": "150",
			"DATE": "12-09-2016",
			"ENCOUNTERID": 13433296,
			"IEP": "201461480",
			"UF": "",
			"ENCOUNTERDATE": ""
		}, {
			"VALUE": "48",
			"DATE": "12-09-2016",
			"ENCOUNTERID": 13433296,
			"IEP": "201461480",
			"UF": "",
			"ENCOUNTERDATE": ""
		}, {
			"VALUE": "120",
			"DATE": "08-09-2016",
			"ENCOUNTERID": 13433296,
			"IEP": "201461480",
			"UF": "",
			"ENCOUNTERDATE": ""
		}]
	}
}